sapulatar_qt/__init__.py
sapulatar_qt/main.py
sapulatar_qt/ui/__init__.py
sapulatar_qt/ui/main_window.py
sapulatar_qt/ui/progress_dialog.py
sapulatar_qt/ui/assets/logo.png
sapulatar_qt-1.0.dev2.data/data/share/applications/sapulatar-qt.desktop
sapulatar_qt-1.0.dev2.data/data/share/icons/sapulatar-qt.png
sapulatar_qt-1.0.dev2.dist-info/METADATA
sapulatar_qt-1.0.dev2.dist-info/WHEEL
sapulatar_qt-1.0.dev2.dist-info/entry_points.txt
sapulatar_qt-1.0.dev2.dist-info/top_level.txt
sapulatar_qt-1.0.dev2.dist-info/RECORD
