Metadata-Version: 2.1
Name: sapulatar-qt
Version: 1.0.dev2
Summary: Simple tool to help you remove background from your images/photos.
Home-page: https://github.com/devlovers-id/sapulatar-qt
Author: Devlovers ID
Author-email: support@dev-is.my.id
License: GPL-3.0
Platform: Windows
Platform: Linux
Platform: Mac OS-X
Requires-Python: >=3.8
Requires-Dist: PySide2 (==5.15.2)
